humps/__init__.py
humps/__init__.pyi
humps/main.py
humps/main.pyi
humps/py.typed
pyhumps-3.7.3.dist-info/LICENSE
pyhumps-3.7.3.dist-info/METADATA
pyhumps-3.7.3.dist-info/WHEEL
pyhumps-3.7.3.dist-info/top_level.txt
pyhumps-3.7.3.dist-info/RECORD
