Metadata-Version: 2.1
Name: pyhumps
Version: 3.7.3
Summary: 🐫  Convert strings (and dictionary keys) between snake case, camel case and pascal case in Python. Inspired by Humps for Node
Home-page: https://github.com/nficano/humps
Author: Nick Ficano
Author-email: nficano@gmail.com
License: The Unlicense (Unlicense)
Keywords: humps,snakecase,convert case,camelcase
Platform: UNKNOWN
Classifier: License :: OSI Approved :: MIT License
Classifier: Programming Language :: Python
Classifier: Programming Language :: Python :: 3
Classifier: Programming Language :: Python :: 3.6
Classifier: Programming Language :: Python :: 3.7
Classifier: Programming Language :: Python :: 3.8
Classifier: Programming Language :: Python :: 3.9
Classifier: Programming Language :: Python :: 3.10
Classifier: Programming Language :: Python :: Implementation :: CPython
Classifier: Programming Language :: Python :: Implementation :: PyPy
License-File: LICENSE
